README.rst
setup.py
stacktraces.py
stacktraces.egg-info/PKG-INFO
stacktraces.egg-info/SOURCES.txt
stacktraces.egg-info/dependency_links.txt
stacktraces.egg-info/pbr.json
stacktraces.egg-info/top_level.txt