Metadata-Version: 1.1
Name: stacktraces
Version: 0.1.0
Summary: Stack and stats tracer for multi-threaded applications.
Home-page: https://github.com/Kronuz/stacktraces
Author: Germán Méndez Bravo
Author-email: german.mb@gmail.com
License: MIT
Platform: UNKNOWN
Classifier: Development Status :: 5 - Production/Stable
Classifier: Intended Audience :: Developers
Classifier: License :: OSI Approved :: MIT License
Classifier: Operating System :: OS Independent
Classifier: Topic :: Software Development :: Libraries
Classifier: Topic :: Utilities
Classifier: Programming Language :: Python :: 2
Classifier: Programming Language :: Python :: 3
